Workbook

Sheet 估值摘要
A1: 可比公司估值摘要
A2: 星河智造（示例000000） | B2: 估值日：2025-04-30 | C2: 币种：CNY
A3: 虚构样例：仅用于演示模型结构与公式联动，不构成投资建议；正式研究必须替换为真实同业、市场数据与可追溯来源。
A5: 目标公司 | B5: 当前股价 | C5: 区间低 | D5: 区间中枢 | E5: 区间高 | F5: 中枢上涨空间
A6: 星河智造 | B6: =同业数据!D2 -> 12.8 | C6: =隐含股价!B9 -> 13.099958 | D6: =隐含股价!C9 -> 14.966529 | E6: =隐含股价!D9 -> 17.356701 | F6: =IF(AND(ISNUMBER(D6),ISNUMBER(B6),B6<>0),D6/B6-1,"") -> 0.1692601
A8: 核心倍数与溢价/折价 | B8: 核心中位数 | C8: 目标公司 | D8: 目标相对核心中位数
A9: EV/营业收入 | B9: =统计!B3 -> 2.1458333 | C9: =统计!B15 -> 1.8587458 | D9: =统计!B16 -> -0.13378837
A10: EV/EBITDA | B10: =统计!C3 -> 11.547826 | C10: =统计!C15 -> 10.07806 | D10: =统计!C16 -> -0.12727643
A11: EV/EBIT | B11: =统计!D3 -> 14.9375 | C11: =统计!D15 -> 14.710822 | D11: =统计!D16 -> -0.015175103
A12: P/E（LTM） | B12: =统计!E3 -> 19.787234 | C12: =统计!E15 -> 16.721643 | D12: =统计!E16 -> -0.1549277
A14: 利润率对比 | B14: 目标公司 | C14: 核心同业中位数 | D14: 差异（百分点）
A15: EBITDA 利润率 | B15: =利润率对比!H16 -> 0.18443488 | C15: =利润率对比!H13 -> 0.2 | D15: =利润率对比!H17 -> -1.556512
A16: EBIT 利润率 | B16: =利润率对比!I16 -> 0.12635227 | C16: =利润率对比!I13 -> 0.15609756 | D16: =利润率对比!I17 -> -2.9745288
A17: 净利率 | B17: =利润率对比!J16 -> 0.10445999 | C17: =利润率对比!J13 -> 0.11388889 | D17: =利润率对比!J17 -> -0.94288973

Sheet 说明
A1: 项目 | B1: 内容
A2: 目标公司 | B2: 星河智造
A3: 代码 | B3: 示例000000
A4: 估值日期 | B4: 2025-04-30
A5: 币种与单位 | B5: CNY；金额百万元，股本百万股，股价与每股价值元
A6: 同业数据 | B6: 输入表：第 2 行为目标公司，其余为同业；可直接修改输入，其他表公式自动重算
A7: 倍数 | B7: 股权价值 = 股价 × 股本；EV = 股权价值 + 有息负债 + 少数股东权益 − 现金 − 非经营性资产；分母 ≤ 0 记 NM
A8: 统计 | B8: 仅核心同业（Core）；P25/P75 按 QUARTILE（与 PERCENTILE.INC 一致）；样本 ≥ 4 时按 IQR 法标记离群，不删除数据
A9: 隐含股价 | B9: 核心同业（剔除离群）P25 / 中位数 / P75 倍数 × 目标公司分母，EV 倍数再扣股权桥后除以股本
A10: 敏感性 | B10: 核心同业（剔除离群）P25 / 中位数 / P75 倍数 × 目标公司 EBITDA 或归母净利润 ±10% 的隐含股价
A11: 来源台账 | B11: 每家公司的数据日期、来源、入选/剔除理由与可信度
A12: 利润率对比 | B12: EBITDA / EBIT / 净利率 = 对应利润 ÷ 营业收入（收入 ≤ 0 记 NM）；核心同业中位数与 P25/P75，目标公司与核心中位数之差（百分点）。目标公司 EBIT 为剔除投资收益与公允价值变动后的经营性口径，同业 EBIT 以来源数据为准
A13: 状态 | B13: senior-review-ready（核心同业 5 家）

Sheet 同业数据
A1: 代码 | B1: 公司 | C1: 分层 | D1: 股价（元） | E1: 股本（百万股） | F1: 有息负债（百万元） | G1: 少数股东权益（百万元） | H1: 现金（百万元） | I1: 非经营性资产（百万元） | J1: 营业收入 LTM（百万元） | K1: EBITDA LTM（百万元） | L1: EBIT LTM（百万元） | M1: 归母净利润 LTM（百万元） | N1: EPS CY1（元） | O1: 数据日期 | P1: 来源 | Q1: 入选理由 | R1: 剔除理由 | S1: 可信度
A2: 示例000000 | B2: 星河智造 | C2: Target | D2: 12.8 | E2: 800 | F2: 1705 | G2: 308.3 | H2: 1356.7 | I2: 0 | J2: 5862.3401 | K2: 1081.22 | L2: 740.72 | M2: 612.38 | O2: 2025-04-30 | P2: 财报抽取 + 估值假设文件 | S2: high
A3: 示例001 | B3: 华宇装备 | C3: Core | D3: 25 | E3: 600 | F3: 2100 | G3: 150 | H3: 1800 | I3: 0 | J3: 7200 | K3: 1500 | L3: 1150 | M3: 820 | N3: 1.55 | O3: 2025-04-30 | P3: 样例数据（虚构） | Q3: 同为新能源装备制造，客户结构相近 | S3: medium
A4: 示例002 | B4: 东岳智能 | C4: Core | D4: 18.6 | E4: 500 | F4: 900 | G4: 60 | H4: 700 | I4: 0 | J4: 4100 | K4: 820 | L4: 640 | M4: 470 | N4: 1.05 | O4: 2025-04-30 | P4: 样例数据（虚构） | Q4: 产品线与目标公司重合度高 | S4: medium
A5: 示例003 | B5: 恒川重工 | C5: Core | D5: 9.8 | E5: 1200 | F5: 3200 | G5: 400 | H5: 1500 | I5: 0 | J5: 9800 | K5: 1650 | L5: 1100 | M5: 680 | N5: 0.64 | O5: 2025-04-30 | P5: 样例数据（虚构） | Q5: 规模更大但商业模式可比 | S5: medium
A6: 示例004 | B6: 远帆新能 | C6: Core | D6: 32.5 | E6: 300 | F6: 400 | G6: 20 | H6: 900 | I6: 0 | J6: 3500 | K6: 700 | L6: 560 | M6: 430 | N6: 1.62 | O6: 2025-04-30 | P6: 样例数据（虚构） | Q6: 细分设备龙头，增速较高 | S6: medium
A7: 示例005 | B7: 启明电气 | C7: Core | D7: 14.2 | E7: 900 | F7: 1500 | G7: 100 | H7: 1100 | I7: 0 | J7: 6300 | K7: 1150 | L7: 820 | M7: 560 | N7: 0.7 | O7: 2025-04-30 | P7: 样例数据（虚构） | Q7: 电气设备配套，周期属性相近 | S7: medium
A8: 示例006 | B8: 北辰精工 | C8: Secondary | D8: 45 | E8: 200 | F8: 200 | G8: 0 | H8: 600 | I8: 0 | J8: 2600 | K8: 520 | L8: 430 | M8: 360 | N8: 2 | O8: 2025-04-30 | P8: 样例数据（虚构） | Q8: 精密部件，利润率显著更高 | S8: medium
A9: 示例007 | B9: 海川控股 | C9: Excluded | D9: 6 | E9: 3000 | F9: 9000 | G9: 1200 | H9: 2500 | I9: 800 | J9: 30000 | K9: 2000 | L9: 900 | M9: -150 | N9: 0.05 | O9: 2025-04-30 | P9: 样例数据（虚构） | R9: 多元化控股，装备业务占比不足20%且当期亏损 | S9: low

Sheet 倍数
A1: 代码 | B1: 公司 | C1: 分层 | D1: 股权价值 | E1: EV | F1: EV/营业收入 | G1: EV/EBITDA | H1: EV/EBIT | I1: P/E（LTM） | J1: P/E（NTM） | K1: EV/营业收入 离群 | L1: EV/EBITDA 离群 | M1: EV/EBIT 离群 | N1: P/E（LTM） 离群 | O1: P/E（NTM） 离群
A2: =同业数据!A2 -> 示例000000 | B2: =同业数据!B2 -> 星河智造 | C2: =同业数据!C2 -> Target | D2: =IF(AND(ISNUMBER(同业数据!D2),ISNUMBER(同业数据!E2)),同业数据!D2*同业数据!E2,"") -> 10240 | E2: =IF(ISNUMBER(D2),D2+N(同业数据!F2)+N(同业数据!G2)-N(同业数据!H2)-N(同业数据!I2),"") -> 10896.6 | F2: =IF(OR(NOT(ISNUMBER(E2)),NOT(ISNUMBER(同业数据!J2))),"",IF(同业数据!J2<=0,"NM",E2/同业数据!J2)) -> 1.8587458 | G2: =IF(OR(NOT(ISNUMBER(E2)),NOT(ISNUMBER(同业数据!K2))),"",IF(同业数据!K2<=0,"NM",E2/同业数据!K2)) -> 10.07806 | H2: =IF(OR(NOT(ISNUMBER(E2)),NOT(ISNUMBER(同业数据!L2))),"",IF(同业数据!L2<=0,"NM",E2/同业数据!L2)) -> 14.710822 | I2: =IF(OR(NOT(ISNUMBER(D2)),NOT(ISNUMBER(同业数据!M2))),"",IF(同业数据!M2<=0,"NM",D2/同业数据!M2)) -> 16.721643 | J2: =IF(OR(NOT(ISNUMBER(同业数据!D2)),NOT(ISNUMBER(同业数据!N2))),"",IF(同业数据!N2<=0,"NM",同业数据!D2/同业数据!N2)) | K2: =IF(AND(C2="Core",ISNUMBER(F2),统计!B$2>=4),IF(OR(F2<统计!B$7,F2>统计!B$8),"离群",""),"") | L2: =IF(AND(C2="Core",ISNUMBER(G2),统计!C$2>=4),IF(OR(G2<统计!C$7,G2>统计!C$8),"离群",""),"") | M2: =IF(AND(C2="Core",ISNUMBER(H2),统计!D$2>=4),IF(OR(H2<统计!D$7,H2>统计!D$8),"离群",""),"") | N2: =IF(AND(C2="Core",ISNUMBER(I2),统计!E$2>=4),IF(OR(I2<统计!E$7,I2>统计!E$8),"离群",""),"") | O2: =IF(AND(C2="Core",ISNUMBER(J2),统计!F$2>=4),IF(OR(J2<统计!F$7,J2>统计!F$8),"离群",""),"")
A3: =同业数据!A3 -> 示例001 | B3: =同业数据!B3 -> 华宇装备 | C3: =同业数据!C3 -> Core | D3: =IF(AND(ISNUMBER(同业数据!D3),ISNUMBER(同业数据!E3)),同业数据!D3*同业数据!E3,"") -> 15000 | E3: =IF(ISNUMBER(D3),D3+N(同业数据!F3)+N(同业数据!G3)-N(同业数据!H3)-N(同业数据!I3),"") -> 15450 | F3: =IF(OR(NOT(ISNUMBER(E3)),NOT(ISNUMBER(同业数据!J3))),"",IF(同业数据!J3<=0,"NM",E3/同业数据!J3)) -> 2.1458333 | G3: =IF(OR(NOT(ISNUMBER(E3)),NOT(ISNUMBER(同业数据!K3))),"",IF(同业数据!K3<=0,"NM",E3/同业数据!K3)) -> 10.3 | H3: =IF(OR(NOT(ISNUMBER(E3)),NOT(ISNUMBER(同业数据!L3))),"",IF(同业数据!L3<=0,"NM",E3/同业数据!L3)) -> 13.434783 | I3: =IF(OR(NOT(ISNUMBER(D3)),NOT(ISNUMBER(同业数据!M3))),"",IF(同业数据!M3<=0,"NM",D3/同业数据!M3)) -> 18.292683 | J3: =IF(OR(NOT(ISNUMBER(同业数据!D3)),NOT(ISNUMBER(同业数据!N3))),"",IF(同业数据!N3<=0,"NM",同业数据!D3/同业数据!N3)) -> 16.129032 | K3: =IF(AND(C3="Core",ISNUMBER(F3),统计!B$2>=4),IF(OR(F3<统计!B$7,F3>统计!B$8),"离群",""),"") | L3: =IF(AND(C3="Core",ISNUMBER(G3),统计!C$2>=4),IF(OR(G3<统计!C$7,G3>统计!C$8),"离群",""),"") | M3: =IF(AND(C3="Core",ISNUMBER(H3),统计!D$2>=4),IF(OR(H3<统计!D$7,H3>统计!D$8),"离群",""),"") | N3: =IF(AND(C3="Core",ISNUMBER(I3),统计!E$2>=4),IF(OR(I3<统计!E$7,I3>统计!E$8),"离群",""),"") | O3: =IF(AND(C3="Core",ISNUMBER(J3),统计!F$2>=4),IF(OR(J3<统计!F$7,J3>统计!F$8),"离群",""),"")
A4: =同业数据!A4 -> 示例002 | B4: =同业数据!B4 -> 东岳智能 | C4: =同业数据!C4 -> Core | D4: =IF(AND(ISNUMBER(同业数据!D4),ISNUMBER(同业数据!E4)),同业数据!D4*同业数据!E4,"") -> 9300 | E4: =IF(ISNUMBER(D4),D4+N(同业数据!F4)+N(同业数据!G4)-N(同业数据!H4)-N(同业数据!I4),"") -> 9560 | F4: =IF(OR(NOT(ISNUMBER(E4)),NOT(ISNUMBER(同业数据!J4))),"",IF(同业数据!J4<=0,"NM",E4/同业数据!J4)) -> 2.3317073 | G4: =IF(OR(NOT(ISNUMBER(E4)),NOT(ISNUMBER(同业数据!K4))),"",IF(同业数据!K4<=0,"NM",E4/同业数据!K4)) -> 11.658537 | H4: =IF(OR(NOT(ISNUMBER(E4)),NOT(ISNUMBER(同业数据!L4))),"",IF(同业数据!L4<=0,"NM",E4/同业数据!L4)) -> 14.9375 | I4: =IF(OR(NOT(ISNUMBER(D4)),NOT(ISNUMBER(同业数据!M4))),"",IF(同业数据!M4<=0,"NM",D4/同业数据!M4)) -> 19.787234 | J4: =IF(OR(NOT(ISNUMBER(同业数据!D4)),NOT(ISNUMBER(同业数据!N4))),"",IF(同业数据!N4<=0,"NM",同业数据!D4/同业数据!N4)) -> 17.714286 | K4: =IF(AND(C4="Core",ISNUMBER(F4),统计!B$2>=4),IF(OR(F4<统计!B$7,F4>统计!B$8),"离群",""),"") | L4: =IF(AND(C4="Core",ISNUMBER(G4),统计!C$2>=4),IF(OR(G4<统计!C$7,G4>统计!C$8),"离群",""),"") | M4: =IF(AND(C4="Core",ISNUMBER(H4),统计!D$2>=4),IF(OR(H4<统计!D$7,H4>统计!D$8),"离群",""),"") | N4: =IF(AND(C4="Core",ISNUMBER(I4),统计!E$2>=4),IF(OR(I4<统计!E$7,I4>统计!E$8),"离群",""),"") | O4: =IF(AND(C4="Core",ISNUMBER(J4),统计!F$2>=4),IF(OR(J4<统计!F$7,J4>统计!F$8),"离群",""),"")
A5: =同业数据!A5 -> 示例003 | B5: =同业数据!B5 -> 恒川重工 | C5: =同业数据!C5 -> Core | D5: =IF(AND(ISNUMBER(同业数据!D5),ISNUMBER(同业数据!E5)),同业数据!D5*同业数据!E5,"") -> 11760 | E5: =IF(ISNUMBER(D5),D5+N(同业数据!F5)+N(同业数据!G5)-N(同业数据!H5)-N(同业数据!I5),"") -> 13860 | F5: =IF(OR(NOT(ISNUMBER(E5)),NOT(ISNUMBER(同业数据!J5))),"",IF(同业数据!J5<=0,"NM",E5/同业数据!J5)) -> 1.4142857 | G5: =IF(OR(NOT(ISNUMBER(E5)),NOT(ISNUMBER(同业数据!K5))),"",IF(同业数据!K5<=0,"NM",E5/同业数据!K5)) -> 8.4 | H5: =IF(OR(NOT(ISNUMBER(E5)),NOT(ISNUMBER(同业数据!L5))),"",IF(同业数据!L5<=0,"NM",E5/同业数据!L5)) -> 12.6 | I5: =IF(OR(NOT(ISNUMBER(D5)),NOT(ISNUMBER(同业数据!M5))),"",IF(同业数据!M5<=0,"NM",D5/同业数据!M5)) -> 17.294118 | J5: =IF(OR(NOT(ISNUMBER(同业数据!D5)),NOT(ISNUMBER(同业数据!N5))),"",IF(同业数据!N5<=0,"NM",同业数据!D5/同业数据!N5)) -> 15.3125 | K5: =IF(AND(C5="Core",ISNUMBER(F5),统计!B$2>=4),IF(OR(F5<统计!B$7,F5>统计!B$8),"离群",""),"") -> 离群 | L5: =IF(AND(C5="Core",ISNUMBER(G5),统计!C$2>=4),IF(OR(G5<统计!C$7,G5>统计!C$8),"离群",""),"") | M5: =IF(AND(C5="Core",ISNUMBER(H5),统计!D$2>=4),IF(OR(H5<统计!D$7,H5>统计!D$8),"离群",""),"") | N5: =IF(AND(C5="Core",ISNUMBER(I5),统计!E$2>=4),IF(OR(I5<统计!E$7,I5>统计!E$8),"离群",""),"") | O5: =IF(AND(C5="Core",ISNUMBER(J5),统计!F$2>=4),IF(OR(J5<统计!F$7,J5>统计!F$8),"离群",""),"")
A6: =同业数据!A6 -> 示例004 | B6: =同业数据!B6 -> 远帆新能 | C6: =同业数据!C6 -> Core | D6: =IF(AND(ISNUMBER(同业数据!D6),ISNUMBER(同业数据!E6)),同业数据!D6*同业数据!E6,"") -> 9750 | E6: =IF(ISNUMBER(D6),D6+N(同业数据!F6)+N(同业数据!G6)-N(同业数据!H6)-N(同业数据!I6),"") -> 9270 | F6: =IF(OR(NOT(ISNUMBER(E6)),NOT(ISNUMBER(同业数据!J6))),"",IF(同业数据!J6<=0,"NM",E6/同业数据!J6)) -> 2.6485714 | G6: =IF(OR(NOT(ISNUMBER(E6)),NOT(ISNUMBER(同业数据!K6))),"",IF(同业数据!K6<=0,"NM",E6/同业数据!K6)) -> 13.242857 | H6: =IF(OR(NOT(ISNUMBER(E6)),NOT(ISNUMBER(同业数据!L6))),"",IF(同业数据!L6<=0,"NM",E6/同业数据!L6)) -> 16.553571 | I6: =IF(OR(NOT(ISNUMBER(D6)),NOT(ISNUMBER(同业数据!M6))),"",IF(同业数据!M6<=0,"NM",D6/同业数据!M6)) -> 22.674419 | J6: =IF(OR(NOT(ISNUMBER(同业数据!D6)),NOT(ISNUMBER(同业数据!N6))),"",IF(同业数据!N6<=0,"NM",同业数据!D6/同业数据!N6)) -> 20.061728 | K6: =IF(AND(C6="Core",ISNUMBER(F6),统计!B$2>=4),IF(OR(F6<统计!B$7,F6>统计!B$8),"离群",""),"") | L6: =IF(AND(C6="Core",ISNUMBER(G6),统计!C$2>=4),IF(OR(G6<统计!C$7,G6>统计!C$8),"离群",""),"") | M6: =IF(AND(C6="Core",ISNUMBER(H6),统计!D$2>=4),IF(OR(H6<统计!D$7,H6>统计!D$8),"离群",""),"") | N6: =IF(AND(C6="Core",ISNUMBER(I6),统计!E$2>=4),IF(OR(I6<统计!E$7,I6>统计!E$8),"离群",""),"") | O6: =IF(AND(C6="Core",ISNUMBER(J6),统计!F$2>=4),IF(OR(J6<统计!F$7,J6>统计!F$8),"离群",""),"")
A7: =同业数据!A7 -> 示例005 | B7: =同业数据!B7 -> 启明电气 | C7: =同业数据!C7 -> Core | D7: =IF(AND(ISNUMBER(同业数据!D7),ISNUMBER(同业数据!E7)),同业数据!D7*同业数据!E7,"") -> 12780 | E7: =IF(ISNUMBER(D7),D7+N(同业数据!F7)+N(同业数据!G7)-N(同业数据!H7)-N(同业数据!I7),"") -> 13280 | F7: =IF(OR(NOT(ISNUMBER(E7)),NOT(ISNUMBER(同业数据!J7))),"",IF(同业数据!J7<=0,"NM",E7/同业数据!J7)) -> 2.1079365 | G7: =IF(OR(NOT(ISNUMBER(E7)),NOT(ISNUMBER(同业数据!K7))),"",IF(同业数据!K7<=0,"NM",E7/同业数据!K7)) -> 11.547826 | H7: =IF(OR(NOT(ISNUMBER(E7)),NOT(ISNUMBER(同业数据!L7))),"",IF(同业数据!L7<=0,"NM",E7/同业数据!L7)) -> 16.195122 | I7: =IF(OR(NOT(ISNUMBER(D7)),NOT(ISNUMBER(同业数据!M7))),"",IF(同业数据!M7<=0,"NM",D7/同业数据!M7)) -> 22.821429 | J7: =IF(OR(NOT(ISNUMBER(同业数据!D7)),NOT(ISNUMBER(同业数据!N7))),"",IF(同业数据!N7<=0,"NM",同业数据!D7/同业数据!N7)) -> 20.285714 | K7: =IF(AND(C7="Core",ISNUMBER(F7),统计!B$2>=4),IF(OR(F7<统计!B$7,F7>统计!B$8),"离群",""),"") | L7: =IF(AND(C7="Core",ISNUMBER(G7),统计!C$2>=4),IF(OR(G7<统计!C$7,G7>统计!C$8),"离群",""),"") | M7: =IF(AND(C7="Core",ISNUMBER(H7),统计!D$2>=4),IF(OR(H7<统计!D$7,H7>统计!D$8),"离群",""),"") | N7: =IF(AND(C7="Core",ISNUMBER(I7),统计!E$2>=4),IF(OR(I7<统计!E$7,I7>统计!E$8),"离群",""),"") | O7: =IF(AND(C7="Core",ISNUMBER(J7),统计!F$2>=4),IF(OR(J7<统计!F$7,J7>统计!F$8),"离群",""),"")
A8: =同业数据!A8 -> 示例006 | B8: =同业数据!B8 -> 北辰精工 | C8: =同业数据!C8 -> Secondary | D8: =IF(AND(ISNUMBER(同业数据!D8),ISNUMBER(同业数据!E8)),同业数据!D8*同业数据!E8,"") -> 9000 | E8: =IF(ISNUMBER(D8),D8+N(同业数据!F8)+N(同业数据!G8)-N(同业数据!H8)-N(同业数据!I8),"") -> 8600 | F8: =IF(OR(NOT(ISNUMBER(E8)),NOT(ISNUMBER(同业数据!J8))),"",IF(同业数据!J8<=0,"NM",E8/同业数据!J8)) -> 3.3076923 | G8: =IF(OR(NOT(ISNUMBER(E8)),NOT(ISNUMBER(同业数据!K8))),"",IF(同业数据!K8<=0,"NM",E8/同业数据!K8)) -> 16.538462 | H8: =IF(OR(NOT(ISNUMBER(E8)),NOT(ISNUMBER(同业数据!L8))),"",IF(同业数据!L8<=0,"NM",E8/同业数据!L8)) -> 20 | I8: =IF(OR(NOT(ISNUMBER(D8)),NOT(ISNUMBER(同业数据!M8))),"",IF(同业数据!M8<=0,"NM",D8/同业数据!M8)) -> 25 | J8: =IF(OR(NOT(ISNUMBER(同业数据!D8)),NOT(ISNUMBER(同业数据!N8))),"",IF(同业数据!N8<=0,"NM",同业数据!D8/同业数据!N8)) -> 22.5 | K8: =IF(AND(C8="Core",ISNUMBER(F8),统计!B$2>=4),IF(OR(F8<统计!B$7,F8>统计!B$8),"离群",""),"") | L8: =IF(AND(C8="Core",ISNUMBER(G8),统计!C$2>=4),IF(OR(G8<统计!C$7,G8>统计!C$8),"离群",""),"") | M8: =IF(AND(C8="Core",ISNUMBER(H8),统计!D$2>=4),IF(OR(H8<统计!D$7,H8>统计!D$8),"离群",""),"") | N8: =IF(AND(C8="Core",ISNUMBER(I8),统计!E$2>=4),IF(OR(I8<统计!E$7,I8>统计!E$8),"离群",""),"") | O8: =IF(AND(C8="Core",ISNUMBER(J8),统计!F$2>=4),IF(OR(J8<统计!F$7,J8>统计!F$8),"离群",""),"")
A9: =同业数据!A9 -> 示例007 | B9: =同业数据!B9 -> 海川控股 | C9: =同业数据!C9 -> Excluded | D9: =IF(AND(ISNUMBER(同业数据!D9),ISNUMBER(同业数据!E9)),同业数据!D9*同业数据!E9,"") -> 18000 | E9: =IF(ISNUMBER(D9),D9+N(同业数据!F9)+N(同业数据!G9)-N(同业数据!H9)-N(同业数据!I9),"") -> 24900 | F9: =IF(OR(NOT(ISNUMBER(E9)),NOT(ISNUMBER(同业数据!J9))),"",IF(同业数据!J9<=0,"NM",E9/同业数据!J9)) -> 0.83 | G9: =IF(OR(NOT(ISNUMBER(E9)),NOT(ISNUMBER(同业数据!K9))),"",IF(同业数据!K9<=0,"NM",E9/同业数据!K9)) -> 12.45 | H9: =IF(OR(NOT(ISNUMBER(E9)),NOT(ISNUMBER(同业数据!L9))),"",IF(同业数据!L9<=0,"NM",E9/同业数据!L9)) -> 27.666667 | I9: =IF(OR(NOT(ISNUMBER(D9)),NOT(ISNUMBER(同业数据!M9))),"",IF(同业数据!M9<=0,"NM",D9/同业数据!M9)) -> NM | J9: =IF(OR(NOT(ISNUMBER(同业数据!D9)),NOT(ISNUMBER(同业数据!N9))),"",IF(同业数据!N9<=0,"NM",同业数据!D9/同业数据!N9)) -> 120 | K9: =IF(AND(C9="Core",ISNUMBER(F9),统计!B$2>=4),IF(OR(F9<统计!B$7,F9>统计!B$8),"离群",""),"") | L9: =IF(AND(C9="Core",ISNUMBER(G9),统计!C$2>=4),IF(OR(G9<统计!C$7,G9>统计!C$8),"离群",""),"") | M9: =IF(AND(C9="Core",ISNUMBER(H9),统计!D$2>=4),IF(OR(H9<统计!D$7,H9>统计!D$8),"离群",""),"") | N9: =IF(AND(C9="Core",ISNUMBER(I9),统计!E$2>=4),IF(OR(I9<统计!E$7,I9>统计!E$8),"离群",""),"") | O9: =IF(AND(C9="Core",ISNUMBER(J9),统计!F$2>=4),IF(OR(J9<统计!F$7,J9>统计!F$8),"离群",""),"")

Sheet 统计
A1: 统计量 | B1: EV/营业收入 | C1: EV/EBITDA | D1: EV/EBIT | E1: P/E（LTM） | F1: P/E（NTM）
A2: 核心同业样本数 | B2: =SUMPRODUCT((倍数!$C$3:$C$9="Core")*ISNUMBER(倍数!F$3:F$9)) -> 5 | C2: =SUMPRODUCT((倍数!$C$3:$C$9="Core")*ISNUMBER(倍数!G$3:G$9)) -> 5 | D2: =SUMPRODUCT((倍数!$C$3:$C$9="Core")*ISNUMBER(倍数!H$3:H$9)) -> 5 | E2: =SUMPRODUCT((倍数!$C$3:$C$9="Core")*ISNUMBER(倍数!I$3:I$9)) -> 5 | F2: =SUMPRODUCT((倍数!$C$3:$C$9="Core")*ISNUMBER(倍数!J$3:J$9)) -> 5
A3: 核心中位数 | B3: {=IF(B2=0,"",MEDIAN(IF((倍数!$C$3:$C$9="Core")*ISNUMBER(倍数!F$3:F$9),倍数!F$3:F$9)))} -> 2.1458333 | C3: {=IF(C2=0,"",MEDIAN(IF((倍数!$C$3:$C$9="Core")*ISNUMBER(倍数!G$3:G$9),倍数!G$3:G$9)))} -> 11.547826 | D3: {=IF(D2=0,"",MEDIAN(IF((倍数!$C$3:$C$9="Core")*ISNUMBER(倍数!H$3:H$9),倍数!H$3:H$9)))} -> 14.9375 | E3: {=IF(E2=0,"",MEDIAN(IF((倍数!$C$3:$C$9="Core")*ISNUMBER(倍数!I$3:I$9),倍数!I$3:I$9)))} -> 19.787234 | F3: {=IF(F2=0,"",MEDIAN(IF((倍数!$C$3:$C$9="Core")*ISNUMBER(倍数!J$3:J$9),倍数!J$3:J$9)))} -> 17.714286
A4: 核心均值 | B4: {=IF(B2=0,"",AVERAGE(IF((倍数!$C$3:$C$9="Core")*ISNUMBER(倍数!F$3:F$9),倍数!F$3:F$9)))} -> 2.1296669 | C4: {=IF(C2=0,"",AVERAGE(IF((倍数!$C$3:$C$9="Core")*ISNUMBER(倍数!G$3:G$9),倍数!G$3:G$9)))} -> 11.029844 | D4: {=IF(D2=0,"",AVERAGE(IF((倍数!$C$3:$C$9="Core")*ISNUMBER(倍数!H$3:H$9),倍数!H$3:H$9)))} -> 14.744195 | E4: {=IF(E2=0,"",AVERAGE(IF((倍数!$C$3:$C$9="Core")*ISNUMBER(倍数!I$3:I$9),倍数!I$3:I$9)))} -> 20.173976 | F4: {=IF(F2=0,"",AVERAGE(IF((倍数!$C$3:$C$9="Core")*ISNUMBER(倍数!J$3:J$9),倍数!J$3:J$9)))} -> 17.900652
A5: 核心 P25 | B5: {=IF(B2=0,"",QUARTILE(IF((倍数!$C$3:$C$9="Core")*ISNUMBER(倍数!F$3:F$9),倍数!F$3:F$9),1))} -> 2.1079365 | C5: {=IF(C2=0,"",QUARTILE(IF((倍数!$C$3:$C$9="Core")*ISNUMBER(倍数!G$3:G$9),倍数!G$3:G$9),1))} -> 10.3 | D5: {=IF(D2=0,"",QUARTILE(IF((倍数!$C$3:$C$9="Core")*ISNUMBER(倍数!H$3:H$9),倍数!H$3:H$9),1))} -> 13.434783 | E5: {=IF(E2=0,"",QUARTILE(IF((倍数!$C$3:$C$9="Core")*ISNUMBER(倍数!I$3:I$9),倍数!I$3:I$9),1))} -> 18.292683 | F5: {=IF(F2=0,"",QUARTILE(IF((倍数!$C$3:$C$9="Core")*ISNUMBER(倍数!J$3:J$9),倍数!J$3:J$9),1))} -> 16.129032
A6: 核心 P75 | B6: {=IF(B2=0,"",QUARTILE(IF((倍数!$C$3:$C$9="Core")*ISNUMBER(倍数!F$3:F$9),倍数!F$3:F$9),3))} -> 2.3317073 | C6: {=IF(C2=0,"",QUARTILE(IF((倍数!$C$3:$C$9="Core")*ISNUMBER(倍数!G$3:G$9),倍数!G$3:G$9),3))} -> 11.658537 | D6: {=IF(D2=0,"",QUARTILE(IF((倍数!$C$3:$C$9="Core")*ISNUMBER(倍数!H$3:H$9),倍数!H$3:H$9),3))} -> 16.195122 | E6: {=IF(E2=0,"",QUARTILE(IF((倍数!$C$3:$C$9="Core")*ISNUMBER(倍数!I$3:I$9),倍数!I$3:I$9),3))} -> 22.674419 | F6: {=IF(F2=0,"",QUARTILE(IF((倍数!$C$3:$C$9="Core")*ISNUMBER(倍数!J$3:J$9),倍数!J$3:J$9),3))} -> 20.061728
A7: IQR 下限（P25 − 1.5×IQR） | B7: =IF(B2=0,"",B5-1.5*(B6-B5)) -> 1.7722803 | C7: =IF(C2=0,"",C5-1.5*(C6-C5)) -> 8.2621951 | D7: =IF(D2=0,"",D5-1.5*(D6-D5)) -> 9.2942736 | E7: =IF(E2=0,"",E5-1.5*(E6-E5)) -> 11.720079 | F7: =IF(F2=0,"",F5-1.5*(F6-F5)) -> 10.229988
A8: IQR 上限（P75 + 1.5×IQR） | B8: =IF(B2=0,"",B6+1.5*(B6-B5)) -> 2.6673635 | C8: =IF(C2=0,"",C6+1.5*(C6-C5)) -> 13.696341 | D8: =IF(D2=0,"",D6+1.5*(D6-D5)) -> 20.335631 | E8: =IF(E2=0,"",E6+1.5*(E6-E5)) -> 29.247022 | F8: =IF(F2=0,"",F6+1.5*(F6-F5)) -> 25.960773
A9: 剔除离群后样本数 | B9: =SUMPRODUCT((倍数!$C$3:$C$9="Core")*ISNUMBER(倍数!F$3:F$9)*(倍数!K$3:K$9="")) -> 4 | C9: =SUMPRODUCT((倍数!$C$3:$C$9="Core")*ISNUMBER(倍数!G$3:G$9)*(倍数!L$3:L$9="")) -> 5 | D9: =SUMPRODUCT((倍数!$C$3:$C$9="Core")*ISNUMBER(倍数!H$3:H$9)*(倍数!M$3:M$9="")) -> 5 | E9: =SUMPRODUCT((倍数!$C$3:$C$9="Core")*ISNUMBER(倍数!I$3:I$9)*(倍数!N$3:N$9="")) -> 5 | F9: =SUMPRODUCT((倍数!$C$3:$C$9="Core")*ISNUMBER(倍数!J$3:J$9)*(倍数!O$3:O$9="")) -> 5
A10: 剔除离群后中位数 | B10: {=IF(B9=0,"",MEDIAN(IF((倍数!$C$3:$C$9="Core")*ISNUMBER(倍数!F$3:F$9)*(倍数!K$3:K$9=""),倍数!F$3:F$9)))} -> 2.2387703 | C10: {=IF(C9=0,"",MEDIAN(IF((倍数!$C$3:$C$9="Core")*ISNUMBER(倍数!G$3:G$9)*(倍数!L$3:L$9=""),倍数!G$3:G$9)))} -> 11.547826 | D10: {=IF(D9=0,"",MEDIAN(IF((倍数!$C$3:$C$9="Core")*ISNUMBER(倍数!H$3:H$9)*(倍数!M$3:M$9=""),倍数!H$3:H$9)))} -> 14.9375 | E10: {=IF(E9=0,"",MEDIAN(IF((倍数!$C$3:$C$9="Core")*ISNUMBER(倍数!I$3:I$9)*(倍数!N$3:N$9=""),倍数!I$3:I$9)))} -> 19.787234 | F10: {=IF(F9=0,"",MEDIAN(IF((倍数!$C$3:$C$9="Core")*ISNUMBER(倍数!J$3:J$9)*(倍数!O$3:O$9=""),倍数!J$3:J$9)))} -> 17.714286
A11: 剔除离群后 P25 | B11: {=IF(B9=0,"",QUARTILE(IF((倍数!$C$3:$C$9="Core")*ISNUMBER(倍数!F$3:F$9)*(倍数!K$3:K$9=""),倍数!F$3:F$9),1))} -> 2.1363591 | C11: {=IF(C9=0,"",QUARTILE(IF((倍数!$C$3:$C$9="Core")*ISNUMBER(倍数!G$3:G$9)*(倍数!L$3:L$9=""),倍数!G$3:G$9),1))} -> 10.3 | D11: {=IF(D9=0,"",QUARTILE(IF((倍数!$C$3:$C$9="Core")*ISNUMBER(倍数!H$3:H$9)*(倍数!M$3:M$9=""),倍数!H$3:H$9),1))} -> 13.434783 | E11: {=IF(E9=0,"",QUARTILE(IF((倍数!$C$3:$C$9="Core")*ISNUMBER(倍数!I$3:I$9)*(倍数!N$3:N$9=""),倍数!I$3:I$9),1))} -> 18.292683 | F11: {=IF(F9=0,"",QUARTILE(IF((倍数!$C$3:$C$9="Core")*ISNUMBER(倍数!J$3:J$9)*(倍数!O$3:O$9=""),倍数!J$3:J$9),1))} -> 16.129032
A12: 剔除离群后 P75 | B12: {=IF(B9=0,"",QUARTILE(IF((倍数!$C$3:$C$9="Core")*ISNUMBER(倍数!F$3:F$9)*(倍数!K$3:K$9=""),倍数!F$3:F$9),3))} -> 2.4109233 | C12: {=IF(C9=0,"",QUARTILE(IF((倍数!$C$3:$C$9="Core")*ISNUMBER(倍数!G$3:G$9)*(倍数!L$3:L$9=""),倍数!G$3:G$9),3))} -> 11.658537 | D12: {=IF(D9=0,"",QUARTILE(IF((倍数!$C$3:$C$9="Core")*ISNUMBER(倍数!H$3:H$9)*(倍数!M$3:M$9=""),倍数!H$3:H$9),3))} -> 16.195122 | E12: {=IF(E9=0,"",QUARTILE(IF((倍数!$C$3:$C$9="Core")*ISNUMBER(倍数!I$3:I$9)*(倍数!N$3:N$9=""),倍数!I$3:I$9),3))} -> 22.674419 | F12: {=IF(F9=0,"",QUARTILE(IF((倍数!$C$3:$C$9="Core")*ISNUMBER(倍数!J$3:J$9)*(倍数!O$3:O$9=""),倍数!J$3:J$9),3))} -> 20.061728
A13: 核心+次要 样本数 | B13: =SUMPRODUCT(((倍数!$C$3:$C$9="Core")+(倍数!$C$3:$C$9="Secondary"))*ISNUMBER(倍数!F$3:F$9)) -> 6 | C13: =SUMPRODUCT(((倍数!$C$3:$C$9="Core")+(倍数!$C$3:$C$9="Secondary"))*ISNUMBER(倍数!G$3:G$9)) -> 6 | D13: =SUMPRODUCT(((倍数!$C$3:$C$9="Core")+(倍数!$C$3:$C$9="Secondary"))*ISNUMBER(倍数!H$3:H$9)) -> 6 | E13: =SUMPRODUCT(((倍数!$C$3:$C$9="Core")+(倍数!$C$3:$C$9="Secondary"))*ISNUMBER(倍数!I$3:I$9)) -> 6 | F13: =SUMPRODUCT(((倍数!$C$3:$C$9="Core")+(倍数!$C$3:$C$9="Secondary"))*ISNUMBER(倍数!J$3:J$9)) -> 6
A14: 核心+次要 中位数 | B14: {=IF(B13=0,"",MEDIAN(IF(((倍数!$C$3:$C$9="Core")+(倍数!$C$3:$C$9="Secondary"))*ISNUMBER(倍数!F$3:F$9),倍数!F$3:F$9)))} -> 2.2387703 | C14: {=IF(C13=0,"",MEDIAN(IF(((倍数!$C$3:$C$9="Core")+(倍数!$C$3:$C$9="Secondary"))*ISNUMBER(倍数!G$3:G$9),倍数!G$3:G$9)))} -> 11.603181 | D14: {=IF(D13=0,"",MEDIAN(IF(((倍数!$C$3:$C$9="Core")+(倍数!$C$3:$C$9="Secondary"))*ISNUMBER(倍数!H$3:H$9),倍数!H$3:H$9)))} -> 15.566311 | E14: {=IF(E13=0,"",MEDIAN(IF(((倍数!$C$3:$C$9="Core")+(倍数!$C$3:$C$9="Secondary"))*ISNUMBER(倍数!I$3:I$9),倍数!I$3:I$9)))} -> 21.230826 | F14: {=IF(F13=0,"",MEDIAN(IF(((倍数!$C$3:$C$9="Core")+(倍数!$C$3:$C$9="Secondary"))*ISNUMBER(倍数!J$3:J$9),倍数!J$3:J$9)))} -> 18.888007
A15: 目标公司倍数 | B15: =倍数!F2 -> 1.8587458 | C15: =倍数!G2 -> 10.07806 | D15: =倍数!H2 -> 14.710822 | E15: =倍数!I2 -> 16.721643 | F15: =倍数!J2
A16: 目标相对核心中位数溢价 | B16: =IF(AND(ISNUMBER(B15),ISNUMBER(B3)),IF(B3<>0,B15/B3-1,""),"") -> -0.13378837 | C16: =IF(AND(ISNUMBER(C15),ISNUMBER(C3)),IF(C3<>0,C15/C3-1,""),"") -> -0.12727643 | D16: =IF(AND(ISNUMBER(D15),ISNUMBER(D3)),IF(D3<>0,D15/D3-1,""),"") -> -0.015175103 | E16: =IF(AND(ISNUMBER(E15),ISNUMBER(E3)),IF(E3<>0,E15/E3-1,""),"") -> -0.1549277 | F16: =IF(AND(ISNUMBER(F15),ISNUMBER(F3)),IF(F3<>0,F15/F3-1,""),"")

Sheet 隐含股价
A1: 倍数 | B1: 目标公司分母（百万元） | C1: 核心样本数（剔除离群） | D1: P25 隐含股价（元） | E1: 中位数隐含股价（元） | F1: P75 隐含股价（元）
A2: EV/EBITDA | B2: =同业数据!K2 -> 1081.22 | C2: =统计!C9 -> 5 | D2: =IF(AND(ISNUMBER(统计!C11),ISNUMBER($B2)),IF(AND($B2>0,N($B$6)<>0),(统计!C11*$B2-$B$5)/$B$6,""),"") -> 13.099958 | E2: =IF(AND(ISNUMBER(统计!C10),ISNUMBER($B2)),IF(AND($B2>0,N($B$6)<>0),(统计!C10*$B2-$B$5)/$B$6,""),"") -> 14.786426 | F2: =IF(AND(ISNUMBER(统计!C12),ISNUMBER($B2)),IF(AND($B2>0,N($B$6)<>0),(统计!C12*$B2-$B$5)/$B$6,""),"") -> 14.936054
A3: P/E（LTM） | B3: =同业数据!M2 -> 612.38 | C3: =统计!E9 -> 5 | D3: =IF(AND(ISNUMBER(统计!E11),ISNUMBER($B3)),IF(AND($B3>0,N($B$6)<>0),统计!E11*$B3/$B$6,""),"") -> 14.002591 | E3: =IF(AND(ISNUMBER(统计!E10),ISNUMBER($B3)),IF(AND($B3>0,N($B$6)<>0),统计!E10*$B3/$B$6,""),"") -> 15.146633 | F3: =IF(AND(ISNUMBER(统计!E12),ISNUMBER($B3)),IF(AND($B3>0,N($B$6)<>0),统计!E12*$B3/$B$6,""),"") -> 17.356701
A5: 股权桥调整（有息负债+少数股东权益−现金−非经营性资产，百万元） | B5: =N(同业数据!F2)+N(同业数据!G2)-N(同业数据!H2)-N(同业数据!I2) -> 656.6
A6: 目标公司股本（百万股） | B6: =同业数据!E2 -> 800
A8: 估值区间 | B8: 低（P25 最小值） | C8: 中（中位数的中位数） | D8: 高（P75 最大值）
A9: 隐含股价（元） | B9: =IF(COUNT(D2:D3)=0,"",MIN(D2:D3)) -> 13.099958 | C9: =IF(COUNT(E2:E3)=0,"",MEDIAN(E2:E3)) -> 14.966529 | D9: =IF(COUNT(F2:F3)=0,"",MAX(F2:F3)) -> 17.356701

Sheet 敏感性
A1: EV/EBITDA 倍数 × EBITDA 变动 → 隐含股价（元）
A2: 倍数档位 | B2: 倍数 | C2: EBITDA -10% | D2: EBITDA -5% | E2: EBITDA +0% | F2: EBITDA +5% | G2: EBITDA +10%
B3: 变动 | C3: -0.1 | D3: -0.05 | E3: 0 | F3: 0.05 | G3: 0.1
A4: P25 | B4: =统计!C11 -> 10.3 | C4: =IF(AND(ISNUMBER($B4),ISNUMBER(隐含股价!$B$2)),IF(N(隐含股价!$B$6)<>0,($B4*隐含股价!$B$2*(1+C$3)-隐含股价!$B$5)/隐含股价!$B$6,""),"") -> 11.707887 | D4: =IF(AND(ISNUMBER($B4),ISNUMBER(隐含股价!$B$2)),IF(N(隐含股价!$B$6)<>0,($B4*隐含股价!$B$2*(1+D$3)-隐含股价!$B$5)/隐含股价!$B$6,""),"") -> 12.403922 | E4: =IF(AND(ISNUMBER($B4),ISNUMBER(隐含股价!$B$2)),IF(N(隐含股价!$B$6)<>0,($B4*隐含股价!$B$2*(1+E$3)-隐含股价!$B$5)/隐含股价!$B$6,""),"") -> 13.099958 | F4: =IF(AND(ISNUMBER($B4),ISNUMBER(隐含股价!$B$2)),IF(N(隐含股价!$B$6)<>0,($B4*隐含股价!$B$2*(1+F$3)-隐含股价!$B$5)/隐含股价!$B$6,""),"") -> 13.795993 | G4: =IF(AND(ISNUMBER($B4),ISNUMBER(隐含股价!$B$2)),IF(N(隐含股价!$B$6)<>0,($B4*隐含股价!$B$2*(1+G$3)-隐含股价!$B$5)/隐含股价!$B$6,""),"") -> 14.492028
A5: 中位数 | B5: =统计!C10 -> 11.547826 | C5: =IF(AND(ISNUMBER($B5),ISNUMBER(隐含股价!$B$2)),IF(N(隐含股价!$B$6)<>0,($B5*隐含股价!$B$2*(1+C$3)-隐含股价!$B$5)/隐含股价!$B$6,""),"") -> 13.225708 | D5: =IF(AND(ISNUMBER($B5),ISNUMBER(隐含股价!$B$2)),IF(N(隐含股价!$B$6)<>0,($B5*隐含股价!$B$2*(1+D$3)-隐含股价!$B$5)/隐含股价!$B$6,""),"") -> 14.006067 | E5: =IF(AND(ISNUMBER($B5),ISNUMBER(隐含股价!$B$2)),IF(N(隐含股价!$B$6)<>0,($B5*隐含股价!$B$2*(1+E$3)-隐含股价!$B$5)/隐含股价!$B$6,""),"") -> 14.786426 | F5: =IF(AND(ISNUMBER($B5),ISNUMBER(隐含股价!$B$2)),IF(N(隐含股价!$B$6)<>0,($B5*隐含股价!$B$2*(1+F$3)-隐含股价!$B$5)/隐含股价!$B$6,""),"") -> 15.566784 | G5: =IF(AND(ISNUMBER($B5),ISNUMBER(隐含股价!$B$2)),IF(N(隐含股价!$B$6)<>0,($B5*隐含股价!$B$2*(1+G$3)-隐含股价!$B$5)/隐含股价!$B$6,""),"") -> 16.347143
A6: P75 | B6: =统计!C12 -> 11.658537 | C6: =IF(AND(ISNUMBER($B6),ISNUMBER(隐含股价!$B$2)),IF(N(隐含股价!$B$6)<>0,($B6*隐含股价!$B$2*(1+C$3)-隐含股价!$B$5)/隐含股价!$B$6,""),"") -> 13.360373 | D6: =IF(AND(ISNUMBER($B6),ISNUMBER(隐含股价!$B$2)),IF(N(隐含股价!$B$6)<>0,($B6*隐含股价!$B$2*(1+D$3)-隐含股价!$B$5)/隐含股价!$B$6,""),"") -> 14.148213 | E6: =IF(AND(ISNUMBER($B6),ISNUMBER(隐含股价!$B$2)),IF(N(隐含股价!$B$6)<>0,($B6*隐含股价!$B$2*(1+E$3)-隐含股价!$B$5)/隐含股价!$B$6,""),"") -> 14.936054 | F6: =IF(AND(ISNUMBER($B6),ISNUMBER(隐含股价!$B$2)),IF(N(隐含股价!$B$6)<>0,($B6*隐含股价!$B$2*(1+F$3)-隐含股价!$B$5)/隐含股价!$B$6,""),"") -> 15.723894 | G6: =IF(AND(ISNUMBER($B6),ISNUMBER(隐含股价!$B$2)),IF(N(隐含股价!$B$6)<>0,($B6*隐含股价!$B$2*(1+G$3)-隐含股价!$B$5)/隐含股价!$B$6,""),"") -> 16.511734
A8: P/E（LTM）倍数 × 归母净利润变动 → 隐含股价（元）
A9: 倍数档位 | B9: 倍数 | C9: 归母净利润 -10% | D9: 归母净利润 -5% | E9: 归母净利润 +0% | F9: 归母净利润 +5% | G9: 归母净利润 +10%
B10: 变动 | C10: -0.1 | D10: -0.05 | E10: 0 | F10: 0.05 | G10: 0.1
A11: P25 | B11: =统计!E11 -> 18.292683 | C11: =IF(AND(ISNUMBER($B11),ISNUMBER(隐含股价!$B$3)),IF(N(隐含股价!$B$6)<>0,$B11*隐含股价!$B$3*(1+C$10)/隐含股价!$B$6,""),"") -> 12.602332 | D11: =IF(AND(ISNUMBER($B11),ISNUMBER(隐含股价!$B$3)),IF(N(隐含股价!$B$6)<>0,$B11*隐含股价!$B$3*(1+D$10)/隐含股价!$B$6,""),"") -> 13.302462 | E11: =IF(AND(ISNUMBER($B11),ISNUMBER(隐含股价!$B$3)),IF(N(隐含股价!$B$6)<>0,$B11*隐含股价!$B$3*(1+E$10)/隐含股价!$B$6,""),"") -> 14.002591 | F11: =IF(AND(ISNUMBER($B11),ISNUMBER(隐含股价!$B$3)),IF(N(隐含股价!$B$6)<>0,$B11*隐含股价!$B$3*(1+F$10)/隐含股价!$B$6,""),"") -> 14.702721 | G11: =IF(AND(ISNUMBER($B11),ISNUMBER(隐含股价!$B$3)),IF(N(隐含股价!$B$6)<>0,$B11*隐含股价!$B$3*(1+G$10)/隐含股价!$B$6,""),"") -> 15.402851
A12: 中位数 | B12: =统计!E10 -> 19.787234 | C12: =IF(AND(ISNUMBER($B12),ISNUMBER(隐含股价!$B$3)),IF(N(隐含股价!$B$6)<>0,$B12*隐含股价!$B$3*(1+C$10)/隐含股价!$B$6,""),"") -> 13.63197 | D12: =IF(AND(ISNUMBER($B12),ISNUMBER(隐含股价!$B$3)),IF(N(隐含股价!$B$6)<>0,$B12*隐含股价!$B$3*(1+D$10)/隐含股价!$B$6,""),"") -> 14.389301 | E12: =IF(AND(ISNUMBER($B12),ISNUMBER(隐含股价!$B$3)),IF(N(隐含股价!$B$6)<>0,$B12*隐含股价!$B$3*(1+E$10)/隐含股价!$B$6,""),"") -> 15.146633 | F12: =IF(AND(ISNUMBER($B12),ISNUMBER(隐含股价!$B$3)),IF(N(隐含股价!$B$6)<>0,$B12*隐含股价!$B$3*(1+F$10)/隐含股价!$B$6,""),"") -> 15.903965 | G12: =IF(AND(ISNUMBER($B12),ISNUMBER(隐含股价!$B$3)),IF(N(隐含股价!$B$6)<>0,$B12*隐含股价!$B$3*(1+G$10)/隐含股价!$B$6,""),"") -> 16.661296
A13: P75 | B13: =统计!E12 -> 22.674419 | C13: =IF(AND(ISNUMBER($B13),ISNUMBER(隐含股价!$B$3)),IF(N(隐含股价!$B$6)<>0,$B13*隐含股价!$B$3*(1+C$10)/隐含股价!$B$6,""),"") -> 15.621031 | D13: =IF(AND(ISNUMBER($B13),ISNUMBER(隐含股价!$B$3)),IF(N(隐含股价!$B$6)<>0,$B13*隐含股价!$B$3*(1+D$10)/隐含股价!$B$6,""),"") -> 16.488866 | E13: =IF(AND(ISNUMBER($B13),ISNUMBER(隐含股价!$B$3)),IF(N(隐含股价!$B$6)<>0,$B13*隐含股价!$B$3*(1+E$10)/隐含股价!$B$6,""),"") -> 17.356701 | F13: =IF(AND(ISNUMBER($B13),ISNUMBER(隐含股价!$B$3)),IF(N(隐含股价!$B$6)<>0,$B13*隐含股价!$B$3*(1+F$10)/隐含股价!$B$6,""),"") -> 18.224536 | G13: =IF(AND(ISNUMBER($B13),ISNUMBER(隐含股价!$B$3)),IF(N(隐含股价!$B$6)<>0,$B13*隐含股价!$B$3*(1+G$10)/隐含股价!$B$6,""),"") -> 19.092371

Sheet 来源台账
A1: 代码 | B1: 公司 | C1: 分层 | D1: 数据日期 | E1: 来源 | F1: 入选理由 | G1: 剔除理由 | H1: 可信度
A2: =同业数据!A2&"" -> 示例000000 | B2: =同业数据!B2&"" -> 星河智造 | C2: =同业数据!C2&"" -> Target | D2: =同业数据!O2&"" -> 2025-04-30 | E2: =同业数据!P2&"" -> 财报抽取 + 估值假设文件 | F2: =同业数据!Q2&"" | G2: =同业数据!R2&"" | H2: =同业数据!S2&"" -> high
A3: =同业数据!A3&"" -> 示例001 | B3: =同业数据!B3&"" -> 华宇装备 | C3: =同业数据!C3&"" -> Core | D3: =同业数据!O3&"" -> 2025-04-30 | E3: =同业数据!P3&"" -> 样例数据（虚构） | F3: =同业数据!Q3&"" -> 同为新能源装备制造，客户结构相近 | G3: =同业数据!R3&"" | H3: =同业数据!S3&"" -> medium
A4: =同业数据!A4&"" -> 示例002 | B4: =同业数据!B4&"" -> 东岳智能 | C4: =同业数据!C4&"" -> Core | D4: =同业数据!O4&"" -> 2025-04-30 | E4: =同业数据!P4&"" -> 样例数据（虚构） | F4: =同业数据!Q4&"" -> 产品线与目标公司重合度高 | G4: =同业数据!R4&"" | H4: =同业数据!S4&"" -> medium
A5: =同业数据!A5&"" -> 示例003 | B5: =同业数据!B5&"" -> 恒川重工 | C5: =同业数据!C5&"" -> Core | D5: =同业数据!O5&"" -> 2025-04-30 | E5: =同业数据!P5&"" -> 样例数据（虚构） | F5: =同业数据!Q5&"" -> 规模更大但商业模式可比 | G5: =同业数据!R5&"" | H5: =同业数据!S5&"" -> medium
A6: =同业数据!A6&"" -> 示例004 | B6: =同业数据!B6&"" -> 远帆新能 | C6: =同业数据!C6&"" -> Core | D6: =同业数据!O6&"" -> 2025-04-30 | E6: =同业数据!P6&"" -> 样例数据（虚构） | F6: =同业数据!Q6&"" -> 细分设备龙头，增速较高 | G6: =同业数据!R6&"" | H6: =同业数据!S6&"" -> medium
A7: =同业数据!A7&"" -> 示例005 | B7: =同业数据!B7&"" -> 启明电气 | C7: =同业数据!C7&"" -> Core | D7: =同业数据!O7&"" -> 2025-04-30 | E7: =同业数据!P7&"" -> 样例数据（虚构） | F7: =同业数据!Q7&"" -> 电气设备配套，周期属性相近 | G7: =同业数据!R7&"" | H7: =同业数据!S7&"" -> medium
A8: =同业数据!A8&"" -> 示例006 | B8: =同业数据!B8&"" -> 北辰精工 | C8: =同业数据!C8&"" -> Secondary | D8: =同业数据!O8&"" -> 2025-04-30 | E8: =同业数据!P8&"" -> 样例数据（虚构） | F8: =同业数据!Q8&"" -> 精密部件，利润率显著更高 | G8: =同业数据!R8&"" | H8: =同业数据!S8&"" -> medium
A9: =同业数据!A9&"" -> 示例007 | B9: =同业数据!B9&"" -> 海川控股 | C9: =同业数据!C9&"" -> Excluded | D9: =同业数据!O9&"" -> 2025-04-30 | E9: =同业数据!P9&"" -> 样例数据（虚构） | F9: =同业数据!Q9&"" | G9: =同业数据!R9&"" -> 多元化控股，装备业务占比不足20%且当期亏损 | H9: =同业数据!S9&"" -> low

Sheet 利润率对比
A1: 代码 | B1: 公司 | C1: 分层 | D1: 营业收入（百万元） | E1: EBITDA（百万元） | F1: EBIT（百万元） | G1: 归母净利润（百万元） | H1: EBITDA 利润率 | I1: EBIT 利润率 | J1: 净利率
A2: =同业数据!A2 -> 示例000000 | B2: =同业数据!B2 -> 星河智造 | C2: =同业数据!C2 -> Target | D2: =IF(ISNUMBER(同业数据!J2),同业数据!J2,"") -> 5862.3401 | E2: =IF(ISNUMBER(同业数据!K2),同业数据!K2,"") -> 1081.22 | F2: =IF(ISNUMBER(同业数据!L2),同业数据!L2,"") -> 740.72 | G2: =IF(ISNUMBER(同业数据!M2),同业数据!M2,"") -> 612.38 | H2: =IF(AND(ISNUMBER(D2),ISNUMBER(E2)),IF(D2<=0,"NM",E2/D2),"") -> 0.18443488 | I2: =IF(AND(ISNUMBER(D2),ISNUMBER(F2)),IF(D2<=0,"NM",F2/D2),"") -> 0.12635227 | J2: =IF(AND(ISNUMBER(D2),ISNUMBER(G2)),IF(D2<=0,"NM",G2/D2),"") -> 0.10445999
A3: =同业数据!A3 -> 示例001 | B3: =同业数据!B3 -> 华宇装备 | C3: =同业数据!C3 -> Core | D3: =IF(ISNUMBER(同业数据!J3),同业数据!J3,"") -> 7200 | E3: =IF(ISNUMBER(同业数据!K3),同业数据!K3,"") -> 1500 | F3: =IF(ISNUMBER(同业数据!L3),同业数据!L3,"") -> 1150 | G3: =IF(ISNUMBER(同业数据!M3),同业数据!M3,"") -> 820 | H3: =IF(AND(ISNUMBER(D3),ISNUMBER(E3)),IF(D3<=0,"NM",E3/D3),"") -> 0.20833333 | I3: =IF(AND(ISNUMBER(D3),ISNUMBER(F3)),IF(D3<=0,"NM",F3/D3),"") -> 0.15972222 | J3: =IF(AND(ISNUMBER(D3),ISNUMBER(G3)),IF(D3<=0,"NM",G3/D3),"") -> 0.11388889
A4: =同业数据!A4 -> 示例002 | B4: =同业数据!B4 -> 东岳智能 | C4: =同业数据!C4 -> Core | D4: =IF(ISNUMBER(同业数据!J4),同业数据!J4,"") -> 4100 | E4: =IF(ISNUMBER(同业数据!K4),同业数据!K4,"") -> 820 | F4: =IF(ISNUMBER(同业数据!L4),同业数据!L4,"") -> 640 | G4: =IF(ISNUMBER(同业数据!M4),同业数据!M4,"") -> 470 | H4: =IF(AND(ISNUMBER(D4),ISNUMBER(E4)),IF(D4<=0,"NM",E4/D4),"") -> 0.2 | I4: =IF(AND(ISNUMBER(D4),ISNUMBER(F4)),IF(D4<=0,"NM",F4/D4),"") -> 0.15609756 | J4: =IF(AND(ISNUMBER(D4),ISNUMBER(G4)),IF(D4<=0,"NM",G4/D4),"") -> 0.11463415
A5: =同业数据!A5 -> 示例003 | B5: =同业数据!B5 -> 恒川重工 | C5: =同业数据!C5 -> Core | D5: =IF(ISNUMBER(同业数据!J5),同业数据!J5,"") -> 9800 | E5: =IF(ISNUMBER(同业数据!K5),同业数据!K5,"") -> 1650 | F5: =IF(ISNUMBER(同业数据!L5),同业数据!L5,"") -> 1100 | G5: =IF(ISNUMBER(同业数据!M5),同业数据!M5,"") -> 680 | H5: =IF(AND(ISNUMBER(D5),ISNUMBER(E5)),IF(D5<=0,"NM",E5/D5),"") -> 0.16836735 | I5: =IF(AND(ISNUMBER(D5),ISNUMBER(F5)),IF(D5<=0,"NM",F5/D5),"") -> 0.1122449 | J5: =IF(AND(ISNUMBER(D5),ISNUMBER(G5)),IF(D5<=0,"NM",G5/D5),"") -> 0.069387755
A6: =同业数据!A6 -> 示例004 | B6: =同业数据!B6 -> 远帆新能 | C6: =同业数据!C6 -> Core | D6: =IF(ISNUMBER(同业数据!J6),同业数据!J6,"") -> 3500 | E6: =IF(ISNUMBER(同业数据!K6),同业数据!K6,"") -> 700 | F6: =IF(ISNUMBER(同业数据!L6),同业数据!L6,"") -> 560 | G6: =IF(ISNUMBER(同业数据!M6),同业数据!M6,"") -> 430 | H6: =IF(AND(ISNUMBER(D6),ISNUMBER(E6)),IF(D6<=0,"NM",E6/D6),"") -> 0.2 | I6: =IF(AND(ISNUMBER(D6),ISNUMBER(F6)),IF(D6<=0,"NM",F6/D6),"") -> 0.16 | J6: =IF(AND(ISNUMBER(D6),ISNUMBER(G6)),IF(D6<=0,"NM",G6/D6),"") -> 0.12285714
A7: =同业数据!A7 -> 示例005 | B7: =同业数据!B7 -> 启明电气 | C7: =同业数据!C7 -> Core | D7: =IF(ISNUMBER(同业数据!J7),同业数据!J7,"") -> 6300 | E7: =IF(ISNUMBER(同业数据!K7),同业数据!K7,"") -> 1150 | F7: =IF(ISNUMBER(同业数据!L7),同业数据!L7,"") -> 820 | G7: =IF(ISNUMBER(同业数据!M7),同业数据!M7,"") -> 560 | H7: =IF(AND(ISNUMBER(D7),ISNUMBER(E7)),IF(D7<=0,"NM",E7/D7),"") -> 0.18253968 | I7: =IF(AND(ISNUMBER(D7),ISNUMBER(F7)),IF(D7<=0,"NM",F7/D7),"") -> 0.13015873 | J7: =IF(AND(ISNUMBER(D7),ISNUMBER(G7)),IF(D7<=0,"NM",G7/D7),"") -> 0.088888889
A8: =同业数据!A8 -> 示例006 | B8: =同业数据!B8 -> 北辰精工 | C8: =同业数据!C8 -> Secondary | D8: =IF(ISNUMBER(同业数据!J8),同业数据!J8,"") -> 2600 | E8: =IF(ISNUMBER(同业数据!K8),同业数据!K8,"") -> 520 | F8: =IF(ISNUMBER(同业数据!L8),同业数据!L8,"") -> 430 | G8: =IF(ISNUMBER(同业数据!M8),同业数据!M8,"") -> 360 | H8: =IF(AND(ISNUMBER(D8),ISNUMBER(E8)),IF(D8<=0,"NM",E8/D8),"") -> 0.2 | I8: =IF(AND(ISNUMBER(D8),ISNUMBER(F8)),IF(D8<=0,"NM",F8/D8),"") -> 0.16538462 | J8: =IF(AND(ISNUMBER(D8),ISNUMBER(G8)),IF(D8<=0,"NM",G8/D8),"") -> 0.13846154
A9: =同业数据!A9 -> 示例007 | B9: =同业数据!B9 -> 海川控股 | C9: =同业数据!C9 -> Excluded | D9: =IF(ISNUMBER(同业数据!J9),同业数据!J9,"") -> 30000 | E9: =IF(ISNUMBER(同业数据!K9),同业数据!K9,"") -> 2000 | F9: =IF(ISNUMBER(同业数据!L9),同业数据!L9,"") -> 900 | G9: =IF(ISNUMBER(同业数据!M9),同业数据!M9,"") -> -150 | H9: =IF(AND(ISNUMBER(D9),ISNUMBER(E9)),IF(D9<=0,"NM",E9/D9),"") -> 0.066666667 | I9: =IF(AND(ISNUMBER(D9),ISNUMBER(F9)),IF(D9<=0,"NM",F9/D9),"") -> 0.03 | J9: =IF(AND(ISNUMBER(D9),ISNUMBER(G9)),IF(D9<=0,"NM",G9/D9),"") -> -0.005
A11: 统计（核心同业） | H11: EBITDA 利润率 | I11: EBIT 利润率 | J11: 净利率
A12: 核心同业样本数 | H12: =SUMPRODUCT(($C$3:$C$9="Core")*ISNUMBER(H$3:H$9)) -> 5 | I12: =SUMPRODUCT(($C$3:$C$9="Core")*ISNUMBER(I$3:I$9)) -> 5 | J12: =SUMPRODUCT(($C$3:$C$9="Core")*ISNUMBER(J$3:J$9)) -> 5
A13: 核心中位数 | H13: {=IF(H12=0,"",MEDIAN(IF(($C$3:$C$9="Core")*ISNUMBER(H$3:H$9),H$3:H$9)))} -> 0.2 | I13: {=IF(I12=0,"",MEDIAN(IF(($C$3:$C$9="Core")*ISNUMBER(I$3:I$9),I$3:I$9)))} -> 0.15609756 | J13: {=IF(J12=0,"",MEDIAN(IF(($C$3:$C$9="Core")*ISNUMBER(J$3:J$9),J$3:J$9)))} -> 0.11388889
A14: 核心 P25 | H14: {=IF(H12=0,"",QUARTILE(IF(($C$3:$C$9="Core")*ISNUMBER(H$3:H$9),H$3:H$9),1))} -> 0.18253968 | I14: {=IF(I12=0,"",QUARTILE(IF(($C$3:$C$9="Core")*ISNUMBER(I$3:I$9),I$3:I$9),1))} -> 0.13015873 | J14: {=IF(J12=0,"",QUARTILE(IF(($C$3:$C$9="Core")*ISNUMBER(J$3:J$9),J$3:J$9),1))} -> 0.088888889
A15: 核心 P75 | H15: {=IF(H12=0,"",QUARTILE(IF(($C$3:$C$9="Core")*ISNUMBER(H$3:H$9),H$3:H$9),3))} -> 0.2 | I15: {=IF(I12=0,"",QUARTILE(IF(($C$3:$C$9="Core")*ISNUMBER(I$3:I$9),I$3:I$9),3))} -> 0.15972222 | J15: {=IF(J12=0,"",QUARTILE(IF(($C$3:$C$9="Core")*ISNUMBER(J$3:J$9),J$3:J$9),3))} -> 0.11463415
A16: 目标公司 | H16: =H2 -> 0.18443488 | I16: =I2 -> 0.12635227 | J16: =J2 -> 0.10445999
A17: 目标 − 核心中位数（百分点） | H17: =IF(AND(ISNUMBER(H2),ISNUMBER(H13)),(H2-H13)*100,"") -> -1.556512 | I17: =IF(AND(ISNUMBER(I2),ISNUMBER(I13)),(I2-I13)*100,"") -> -2.9745288 | J17: =IF(AND(ISNUMBER(J2),ISNUMBER(J13)),(J2-J13)*100,"") -> -0.94288973
